LonginusPyPiAlpha/LClient.py
LonginusPyPiAlpha/LServer.py
LonginusPyPiAlpha/LonginusP.py
LonginusPyPiAlpha/Lshell.py
LonginusPyPiAlpha/__init__.py
LonginusPyPiAlpha/diffie-hellman.py
LonginusPyPiAlpha-0.4.9.dist-info/METADATA
LonginusPyPiAlpha-0.4.9.dist-info/WHEEL
LonginusPyPiAlpha-0.4.9.dist-info/top_level.txt
LonginusPyPiAlpha-0.4.9.dist-info/RECORD
